{
  "movies": [
    {
      "id": "m3",
      "title": "Paper Lanterns",
      "genre": [
        "Drama"
      ],
      "duration": 109,
      "rating": "4.7",
      "ageRating": "PG-13",
      "synopsis": "A family-run night market becomes the backdrop for a quiet reunion none of the vendors expected.",
      "releaseDate": "2025-10-24"
    },
    {
      "id": "m4",
      "title": "Borrowed Summer",
      "genre": [
        "Comedy",
        "Drama"
      ],
      "duration": 101,
      "rating": "3.9",
      "ageRating": "PG-13",
      "synopsis": "Two cousins fake a beach vacation online while getting stuck house-sitting in their own hometown.",
      "releaseDate": "2025-07-11"
    },
    {
      "id": "m1",
      "title": "Night Ledger",
      "genre": [
        "Thriller"
      ],
      "duration": 155,
      "rating": "4.4",
      "ageRating": "PG-13",
      "synopsis": "A financial crimes reporter discovers that every missing entry in a company ledger marks a planned disappearance.",
      "releaseDate": "2025-09-12"
    },
    {
      "id": "m2",
      "title": "Cold Signal",
      "genre": [
        "Thriller"
      ],
      "duration": 105,
      "rating": "3.8",
      "ageRating": "PG-13",
      "synopsis": "A late-night radio engineer pieces together a kidnapping from signals hidden between station IDs.",
      "releaseDate": "2025-04-18"
    }
  ],
  "theaters": [
    {
      "id": "t2",
      "name": "Midtown Screens",
      "location": "Midtown District",
      "screenCount": 8,
      "distanceMiles": 8.2,
      "amenities": [
        "Reserved Seating",
        "Dolby Atmos"
      ]
    },
    {
      "id": "t1",
      "name": "Riverview Cinema",
      "location": "Riverview Square",
      "screenCount": 6,
      "distanceMiles": 3.4,
      "amenities": [
        "Reserved Seating"
      ]
    }
  ],
  "showings": [
    {
      "id": "s_m3_t2_20260312_1720",
      "movieId": "m3",
      "theaterId": "t2",
      "screenNumber": 5,
      "date": "2026-03-12",
      "time": "17:20",
      "format": "Standard",
      "totalSeats": 48
    },
    {
      "id": "s_m3_t2_20260312_1910",
      "movieId": "m3",
      "theaterId": "t2",
      "screenNumber": 5,
      "date": "2026-03-12",
      "time": "19:10",
      "format": "Standard",
      "totalSeats": 48
    },
    {
      "id": "s_m3_t2_20260312_2100",
      "movieId": "m3",
      "theaterId": "t2",
      "screenNumber": 5,
      "date": "2026-03-12",
      "time": "21:00",
      "format": "Standard",
      "totalSeats": 48
    },
    {
      "id": "s_m3_t2_20260313_1720",
      "movieId": "m3",
      "theaterId": "t2",
      "screenNumber": 5,
      "date": "2026-03-13",
      "time": "17:20",
      "format": "Standard",
      "totalSeats": 48
    },
    {
      "id": "s_m3_t2_20260313_1910",
      "movieId": "m3",
      "theaterId": "t2",
      "screenNumber": 5,
      "date": "2026-03-13",
      "time": "19:10",
      "format": "Standard",
      "totalSeats": 48
    },
    {
      "id": "s_m3_t2_20260313_2100",
      "movieId": "m3",
      "theaterId": "t2",
      "screenNumber": 5,
      "date": "2026-03-13",
      "time": "21:00",
      "format": "Standard",
      "totalSeats": 48
    },
    {
      "id": "s_m3_t2_20260314_1720",
      "movieId": "m3",
      "theaterId": "t2",
      "screenNumber": 5,
      "date": "2026-03-14",
      "time": "17:20",
      "format": "Standard",
      "totalSeats": 48
    },
    {
      "id": "s_m3_t2_20260314_1910",
      "movieId": "m3",
      "theaterId": "t2",
      "screenNumber": 5,
      "date": "2026-03-14",
      "time": "19:10",
      "format": "Standard",
      "totalSeats": 48
    },
    {
      "id": "s_m3_t2_20260314_2100",
      "movieId": "m3",
      "theaterId": "t2",
      "screenNumber": 5,
      "date": "2026-03-14",
      "time": "21:00",
      "format": "Standard",
      "totalSeats": 48
    },
    {
      "id": "s_m3_t2_20260315_1720",
      "movieId": "m3",
      "theaterId": "t2",
      "screenNumber": 5,
      "date": "2026-03-15",
      "time": "17:20",
      "format": "Standard",
      "totalSeats": 48
    },
    {
      "id": "s_m3_t2_20260315_1910",
      "movieId": "m3",
      "theaterId": "t2",
      "screenNumber": 5,
      "date": "2026-03-15",
      "time": "19:10",
      "format": "Standard",
      "totalSeats": 48
    },
    {
      "id": "s_m3_t2_20260315_2100",
      "movieId": "m3",
      "theaterId": "t2",
      "screenNumber": 5,
      "date": "2026-03-15",
      "time": "21:00",
      "format": "Standard",
      "totalSeats": 48
    },
    {
      "id": "s_m3_t2_20260316_1720",
      "movieId": "m3",
      "theaterId": "t2",
      "screenNumber": 5,
      "date": "2026-03-16",
      "time": "17:20",
      "format": "Standard",
      "totalSeats": 48
    },
    {
      "id": "s_m3_t2_20260316_1910",
      "movieId": "m3",
      "theaterId": "t2",
      "screenNumber": 5,
      "date": "2026-03-16",
      "time": "19:10",
      "format": "Standard",
      "totalSeats": 48
    },
    {
      "id": "s_m3_t2_20260316_2100",
      "movieId": "m3",
      "theaterId": "t2",
      "screenNumber": 5,
      "date": "2026-03-16",
      "time": "21:00",
      "format": "Standard",
      "totalSeats": 48
    },
    {
      "id": "s_m3_t1_20260312_1720",
      "movieId": "m3",
      "theaterId": "t1",
      "screenNumber": 4,
      "date": "2026-03-12",
      "time": "17:20",
      "format": "Standard",
      "totalSeats": 48
    },
    {
      "id": "s_m3_t1_20260312_1910",
      "movieId": "m3",
      "theaterId": "t1",
      "screenNumber": 4,
      "date": "2026-03-12",
      "time": "19:10",
      "format": "Standard",
      "totalSeats": 48
    },
    {
      "id": "s_m3_t1_20260312_2100",
      "movieId": "m3",
      "theaterId": "t1",
      "screenNumber": 4,
      "date": "2026-03-12",
      "time": "21:00",
      "format": "Standard",
      "totalSeats": 48
    },
    {
      "id": "s_m3_t1_20260313_1720",
      "movieId": "m3",
      "theaterId": "t1",
      "screenNumber": 4,
      "date": "2026-03-13",
      "time": "17:20",
      "format": "Standard",
      "totalSeats": 48
    },
    {
      "id": "s_m3_t1_20260313_1910",
      "movieId": "m3",
      "theaterId": "t1",
      "screenNumber": 4,
      "date": "2026-03-13",
      "time": "19:10",
      "format": "Standard",
      "totalSeats": 48
    },
    {
      "id": "s_m3_t1_20260313_2100",
      "movieId": "m3",
      "theaterId": "t1",
      "screenNumber": 4,
      "date": "2026-03-13",
      "time": "21:00",
      "format": "Standard",
      "totalSeats": 48
    },
    {
      "id": "s_m3_t1_20260314_1720",
      "movieId": "m3",
      "theaterId": "t1",
      "screenNumber": 4,
      "date": "2026-03-14",
      "time": "17:20",
      "format": "Standard",
      "totalSeats": 48
    },
    {
      "id": "s_m3_t1_20260314_1910",
      "movieId": "m3",
      "theaterId": "t1",
      "screenNumber": 4,
      "date": "2026-03-14",
      "time": "19:10",
      "format": "Standard",
      "totalSeats": 48
    },
    {
      "id": "s_m3_t1_20260314_2100",
      "movieId": "m3",
      "theaterId": "t1",
      "screenNumber": 4,
      "date": "2026-03-14",
      "time": "21:00",
      "format": "Standard",
      "totalSeats": 48
    },
    {
      "id": "s_m3_t1_20260315_1720",
      "movieId": "m3",
      "theaterId": "t1",
      "screenNumber": 4,
      "date": "2026-03-15",
      "time": "17:20",
      "format": "Standard",
      "totalSeats": 48
    },
    {
      "id": "s_m3_t1_20260315_1910",
      "movieId": "m3",
      "theaterId": "t1",
      "screenNumber": 4,
      "date": "2026-03-15",
      "time": "19:10",
      "format": "Standard",
      "totalSeats": 48
    },
    {
      "id": "s_m3_t1_20260315_2100",
      "movieId": "m3",
      "theaterId": "t1",
      "screenNumber": 4,
      "date": "2026-03-15",
      "time": "21:00",
      "format": "Standard",
      "totalSeats": 48
    },
    {
      "id": "s_m3_t1_20260316_1720",
      "movieId": "m3",
      "theaterId": "t1",
      "screenNumber": 4,
      "date": "2026-03-16",
      "time": "17:20",
      "format": "Standard",
      "totalSeats": 48
    },
    {
      "id": "s_m3_t1_20260316_1910",
      "movieId": "m3",
      "theaterId": "t1",
      "screenNumber": 4,
      "date": "2026-03-16",
      "time": "19:10",
      "format": "Standard",
      "totalSeats": 48
    },
    {
      "id": "s_m3_t1_20260316_2100",
      "movieId": "m3",
      "theaterId": "t1",
      "screenNumber": 4,
      "date": "2026-03-16",
      "time": "21:00",
      "format": "Standard",
      "totalSeats": 48
    },
    {
      "id": "s_m4_t2_20260312_1720",
      "movieId": "m4",
      "theaterId": "t2",
      "screenNumber": 6,
      "date": "2026-03-12",
      "time": "17:20",
      "format": "Standard",
      "totalSeats": 48
    },
    {
      "id": "s_m4_t2_20260312_1910",
      "movieId": "m4",
      "theaterId": "t2",
      "screenNumber": 6,
      "date": "2026-03-12",
      "time": "19:10",
      "format": "Standard",
      "totalSeats": 48
    },
    {
      "id": "s_m4_t2_20260312_2100",
      "movieId": "m4",
      "theaterId": "t2",
      "screenNumber": 6,
      "date": "2026-03-12",
      "time": "21:00",
      "format": "Standard",
      "totalSeats": 48
    },
    {
      "id": "s_m4_t2_20260313_1720",
      "movieId": "m4",
      "theaterId": "t2",
      "screenNumber": 6,
      "date": "2026-03-13",
      "time": "17:20",
      "format": "Standard",
      "totalSeats": 48
    },
    {
      "id": "s_m4_t2_20260313_1910",
      "movieId": "m4",
      "theaterId": "t2",
      "screenNumber": 6,
      "date": "2026-03-13",
      "time": "19:10",
      "format": "Standard",
      "totalSeats": 48
    },
    {
      "id": "s_m4_t2_20260313_2100",
      "movieId": "m4",
      "theaterId": "t2",
      "screenNumber": 6,
      "date": "2026-03-13",
      "time": "21:00",
      "format": "Standard",
      "totalSeats": 48
    },
    {
      "id": "s_m4_t2_20260314_1720",
      "movieId": "m4",
      "theaterId": "t2",
      "screenNumber": 6,
      "date": "2026-03-14",
      "time": "17:20",
      "format": "Standard",
      "totalSeats": 48
    },
    {
      "id": "s_m4_t2_20260314_1910",
      "movieId": "m4",
      "theaterId": "t2",
      "screenNumber": 6,
      "date": "2026-03-14",
      "time": "19:10",
      "format": "Standard",
      "totalSeats": 48
    },
    {
      "id": "s_m4_t2_20260314_2100",
      "movieId": "m4",
      "theaterId": "t2",
      "screenNumber": 6,
      "date": "2026-03-14",
      "time": "21:00",
      "format": "Standard",
      "totalSeats": 48
    },
    {
      "id": "s_m4_t2_20260315_1720",
      "movieId": "m4",
      "theaterId": "t2",
      "screenNumber": 6,
      "date": "2026-03-15",
      "time": "17:20",
      "format": "Standard",
      "totalSeats": 48
    },
    {
      "id": "s_m4_t2_20260315_1910",
      "movieId": "m4",
      "theaterId": "t2",
      "screenNumber": 6,
      "date": "2026-03-15",
      "time": "19:10",
      "format": "Standard",
      "totalSeats": 48
    },
    {
      "id": "s_m4_t2_20260315_2100",
      "movieId": "m4",
      "theaterId": "t2",
      "screenNumber": 6,
      "date": "2026-03-15",
      "time": "21:00",
      "format": "Standard",
      "totalSeats": 48
    },
    {
      "id": "s_m4_t2_20260316_1720",
      "movieId": "m4",
      "theaterId": "t2",
      "screenNumber": 6,
      "date": "2026-03-16",
      "time": "17:20",
      "format": "Standard",
      "totalSeats": 48
    },
    {
      "id": "s_m4_t2_20260316_1910",
      "movieId": "m4",
      "theaterId": "t2",
      "screenNumber": 6,
      "date": "2026-03-16",
      "time": "19:10",
      "format": "Standard",
      "totalSeats": 48
    },
    {
      "id": "s_m4_t2_20260316_2100",
      "movieId": "m4",
      "theaterId": "t2",
      "screenNumber": 6,
      "date": "2026-03-16",
      "time": "21:00",
      "format": "Standard",
      "totalSeats": 48
    },
    {
      "id": "s_m4_t1_20260312_1720",
      "movieId": "m4",
      "theaterId": "t1",
      "screenNumber": 5,
      "date": "2026-03-12",
      "time": "17:20",
      "format": "Standard",
      "totalSeats": 48
    },
    {
      "id": "s_m4_t1_20260312_1910",
      "movieId": "m4",
      "theaterId": "t1",
      "screenNumber": 5,
      "date": "2026-03-12",
      "time": "19:10",
      "format": "Standard",
      "totalSeats": 48
    },
    {
      "id": "s_m4_t1_20260312_2100",
      "movieId": "m4",
      "theaterId": "t1",
      "screenNumber": 5,
      "date": "2026-03-12",
      "time": "21:00",
      "format": "Standard",
      "totalSeats": 48
    },
    {
      "id": "s_m4_t1_20260313_1720",
      "movieId": "m4",
      "theaterId": "t1",
      "screenNumber": 5,
      "date": "2026-03-13",
      "time": "17:20",
      "format": "Standard",
      "totalSeats": 48
    },
    {
      "id": "s_m4_t1_20260313_1910",
      "movieId": "m4",
      "theaterId": "t1",
      "screenNumber": 5,
      "date": "2026-03-13",
      "time": "19:10",
      "format": "Standard",
      "totalSeats": 48
    },
    {
      "id": "s_m4_t1_20260313_2100",
      "movieId": "m4",
      "theaterId": "t1",
      "screenNumber": 5,
      "date": "2026-03-13",
      "time": "21:00",
      "format": "Standard",
      "totalSeats": 48
    },
    {
      "id": "s_m4_t1_20260314_1720",
      "movieId": "m4",
      "theaterId": "t1",
      "screenNumber": 5,
      "date": "2026-03-14",
      "time": "17:20",
      "format": "Standard",
      "totalSeats": 48
    },
    {
      "id": "s_m4_t1_20260314_1910",
      "movieId": "m4",
      "theaterId": "t1",
      "screenNumber": 5,
      "date": "2026-03-14",
      "time": "19:10",
      "format": "Standard",
      "totalSeats": 48
    },
    {
      "id": "s_m4_t1_20260314_2100",
      "movieId": "m4",
      "theaterId": "t1",
      "screenNumber": 5,
      "date": "2026-03-14",
      "time": "21:00",
      "format": "Standard",
      "totalSeats": 48
    },
    {
      "id": "s_m4_t1_20260315_1720",
      "movieId": "m4",
      "theaterId": "t1",
      "screenNumber": 5,
      "date": "2026-03-15",
      "time": "17:20",
      "format": "Standard",
      "totalSeats": 48
    },
    {
      "id": "s_m4_t1_20260315_1910",
      "movieId": "m4",
      "theaterId": "t1",
      "screenNumber": 5,
      "date": "2026-03-15",
      "time": "19:10",
      "format": "Standard",
      "totalSeats": 48
    },
    {
      "id": "s_m4_t1_20260315_2100",
      "movieId": "m4",
      "theaterId": "t1",
      "screenNumber": 5,
      "date": "2026-03-15",
      "time": "21:00",
      "format": "Standard",
      "totalSeats": 48
    },
    {
      "id": "s_m4_t1_20260316_1720",
      "movieId": "m4",
      "theaterId": "t1",
      "screenNumber": 5,
      "date": "2026-03-16",
      "time": "17:20",
      "format": "Standard",
      "totalSeats": 48
    },
    {
      "id": "s_m4_t1_20260316_1910",
      "movieId": "m4",
      "theaterId": "t1",
      "screenNumber": 5,
      "date": "2026-03-16",
      "time": "19:10",
      "format": "Standard",
      "totalSeats": 48
    },
    {
      "id": "s_m4_t1_20260316_2100",
      "movieId": "m4",
      "theaterId": "t1",
      "screenNumber": 5,
      "date": "2026-03-16",
      "time": "21:00",
      "format": "Standard",
      "totalSeats": 48
    },
    {
      "id": "s_m1_t2_20260312_1730",
      "movieId": "m1",
      "theaterId": "t2",
      "screenNumber": 2,
      "date": "2026-03-12",
      "time": "17:30",
      "format": "Standard",
      "totalSeats": 48
    },
    {
      "id": "s_m1_t2_20260312_1900",
      "movieId": "m1",
      "theaterId": "t2",
      "screenNumber": 2,
      "date": "2026-03-12",
      "time": "19:00",
      "format": "Standard",
      "totalSeats": 48
    },
    {
      "id": "s_m1_t2_20260312_2030",
      "movieId": "m1",
      "theaterId": "t2",
      "screenNumber": 2,
      "date": "2026-03-12",
      "time": "20:30",
      "format": "Standard",
      "totalSeats": 48
    },
    {
      "id": "s_m1_t2_20260313_1730",
      "movieId": "m1",
      "theaterId": "t2",
      "screenNumber": 2,
      "date": "2026-03-13",
      "time": "17:30",
      "format": "Standard",
      "totalSeats": 48
    },
    {
      "id": "s_m1_t2_20260313_1900",
      "movieId": "m1",
      "theaterId": "t2",
      "screenNumber": 2,
      "date": "2026-03-13",
      "time": "19:00",
      "format": "Standard",
      "totalSeats": 48
    },
    {
      "id": "s_m1_t2_20260313_2030",
      "movieId": "m1",
      "theaterId": "t2",
      "screenNumber": 2,
      "date": "2026-03-13",
      "time": "20:30",
      "format": "Standard",
      "totalSeats": 48
    },
    {
      "id": "s_m1_t2_20260314_1730",
      "movieId": "m1",
      "theaterId": "t2",
      "screenNumber": 2,
      "date": "2026-03-14",
      "time": "17:30",
      "format": "Standard",
      "totalSeats": 48
    },
    {
      "id": "s_m1_t2_20260314_1900",
      "movieId": "m1",
      "theaterId": "t2",
      "screenNumber": 2,
      "date": "2026-03-14",
      "time": "19:00",
      "format": "Standard",
      "totalSeats": 48
    },
    {
      "id": "s_m1_t2_20260314_2030",
      "movieId": "m1",
      "theaterId": "t2",
      "screenNumber": 2,
      "date": "2026-03-14",
      "time": "20:30",
      "format": "Standard",
      "totalSeats": 48
    },
    {
      "id": "s_m1_t2_20260315_1730",
      "movieId": "m1",
      "theaterId": "t2",
      "screenNumber": 2,
      "date": "2026-03-15",
      "time": "17:30",
      "format": "Standard",
      "totalSeats": 48
    },
    {
      "id": "s_m1_t2_20260315_1900",
      "movieId": "m1",
      "theaterId": "t2",
      "screenNumber": 2,
      "date": "2026-03-15",
      "time": "19:00",
      "format": "Standard",
      "totalSeats": 48
    },
    {
      "id": "s_m1_t2_20260315_2030",
      "movieId": "m1",
      "theaterId": "t2",
      "screenNumber": 2,
      "date": "2026-03-15",
      "time": "20:30",
      "format": "Standard",
      "totalSeats": 48
    },
    {
      "id": "s_m1_t2_20260316_1730",
      "movieId": "m1",
      "theaterId": "t2",
      "screenNumber": 2,
      "date": "2026-03-16",
      "time": "17:30",
      "format": "Standard",
      "totalSeats": 48
    },
    {
      "id": "s_m1_t2_20260316_1900",
      "movieId": "m1",
      "theaterId": "t2",
      "screenNumber": 2,
      "date": "2026-03-16",
      "time": "19:00",
      "format": "Standard",
      "totalSeats": 48
    },
    {
      "id": "s_m1_t2_20260316_2030",
      "movieId": "m1",
      "theaterId": "t2",
      "screenNumber": 2,
      "date": "2026-03-16",
      "time": "20:30",
      "format": "Standard",
      "totalSeats": 48
    },
    {
      "id": "s_m1_t1_20260312_1730",
      "movieId": "m1",
      "theaterId": "t1",
      "screenNumber": 1,
      "date": "2026-03-12",
      "time": "17:30",
      "format": "Standard",
      "totalSeats": 48
    },
    {
      "id": "s_m1_t1_20260312_1900",
      "movieId": "m1",
      "theaterId": "t1",
      "screenNumber": 1,
      "date": "2026-03-12",
      "time": "19:00",
      "format": "Standard",
      "totalSeats": 48
    },
    {
      "id": "s_m1_t1_20260312_2030",
      "movieId": "m1",
      "theaterId": "t1",
      "screenNumber": 1,
      "date": "2026-03-12",
      "time": "20:30",
      "format": "Standard",
      "totalSeats": 48
    },
    {
      "id": "s_m1_t1_20260313_1730",
      "movieId": "m1",
      "theaterId": "t1",
      "screenNumber": 1,
      "date": "2026-03-13",
      "time": "17:30",
      "format": "Standard",
      "totalSeats": 48
    },
    {
      "id": "s_m1_t1_20260313_1900",
      "movieId": "m1",
      "theaterId": "t1",
      "screenNumber": 1,
      "date": "2026-03-13",
      "time": "19:00",
      "format": "Standard",
      "totalSeats": 48
    },
    {
      "id": "s_m1_t1_20260313_2030",
      "movieId": "m1",
      "theaterId": "t1",
      "screenNumber": 1,
      "date": "2026-03-13",
      "time": "20:30",
      "format": "Standard",
      "totalSeats": 48
    },
    {
      "id": "s_m1_t1_20260314_1730",
      "movieId": "m1",
      "theaterId": "t1",
      "screenNumber": 1,
      "date": "2026-03-14",
      "time": "17:30",
      "format": "Standard",
      "totalSeats": 48
    },
    {
      "id": "s_m1_t1_20260314_1900",
      "movieId": "m1",
      "theaterId": "t1",
      "screenNumber": 1,
      "date": "2026-03-14",
      "time": "19:00",
      "format": "Standard",
      "totalSeats": 48
    },
    {
      "id": "s_m1_t1_20260314_2030",
      "movieId": "m1",
      "theaterId": "t1",
      "screenNumber": 1,
      "date": "2026-03-14",
      "time": "20:30",
      "format": "Standard",
      "totalSeats": 48
    },
    {
      "id": "s_m1_t1_20260315_1730",
      "movieId": "m1",
      "theaterId": "t1",
      "screenNumber": 1,
      "date": "2026-03-15",
      "time": "17:30",
      "format": "Standard",
      "totalSeats": 48
    },
    {
      "id": "s_m1_t1_20260315_1900",
      "movieId": "m1",
      "theaterId": "t1",
      "screenNumber": 1,
      "date": "2026-03-15",
      "time": "19:00",
      "format": "Standard",
      "totalSeats": 48
    },
    {
      "id": "s_m1_t1_20260315_2030",
      "movieId": "m1",
      "theaterId": "t1",
      "screenNumber": 1,
      "date": "2026-03-15",
      "time": "20:30",
      "format": "Standard",
      "totalSeats": 48
    },
    {
      "id": "s_m1_t1_20260316_1730",
      "movieId": "m1",
      "theaterId": "t1",
      "screenNumber": 1,
      "date": "2026-03-16",
      "time": "17:30",
      "format": "Standard",
      "totalSeats": 48
    },
    {
      "id": "s_m1_t1_20260316_1900",
      "movieId": "m1",
      "theaterId": "t1",
      "screenNumber": 1,
      "date": "2026-03-16",
      "time": "19:00",
      "format": "Standard",
      "totalSeats": 48
    },
    {
      "id": "s_m1_t1_20260316_2030",
      "movieId": "m1",
      "theaterId": "t1",
      "screenNumber": 1,
      "date": "2026-03-16",
      "time": "20:30",
      "format": "Standard",
      "totalSeats": 48
    },
    {
      "id": "s_m2_t2_20260312_1730",
      "movieId": "m2",
      "theaterId": "t2",
      "screenNumber": 3,
      "date": "2026-03-12",
      "time": "17:30",
      "format": "Standard",
      "totalSeats": 48
    },
    {
      "id": "s_m2_t2_20260312_1900",
      "movieId": "m2",
      "theaterId": "t2",
      "screenNumber": 3,
      "date": "2026-03-12",
      "time": "19:00",
      "format": "Standard",
      "totalSeats": 48
    },
    {
      "id": "s_m2_t2_20260312_2030",
      "movieId": "m2",
      "theaterId": "t2",
      "screenNumber": 3,
      "date": "2026-03-12",
      "time": "20:30",
      "format": "Standard",
      "totalSeats": 48
    },
    {
      "id": "s_m2_t2_20260313_1730",
      "movieId": "m2",
      "theaterId": "t2",
      "screenNumber": 3,
      "date": "2026-03-13",
      "time": "17:30",
      "format": "Standard",
      "totalSeats": 48
    },
    {
      "id": "s_m2_t2_20260313_1900",
      "movieId": "m2",
      "theaterId": "t2",
      "screenNumber": 3,
      "date": "2026-03-13",
      "time": "19:00",
      "format": "Standard",
      "totalSeats": 48
    },
    {
      "id": "s_m2_t2_20260313_2030",
      "movieId": "m2",
      "theaterId": "t2",
      "screenNumber": 3,
      "date": "2026-03-13",
      "time": "20:30",
      "format": "Standard",
      "totalSeats": 48
    },
    {
      "id": "s_m2_t2_20260314_1730",
      "movieId": "m2",
      "theaterId": "t2",
      "screenNumber": 3,
      "date": "2026-03-14",
      "time": "17:30",
      "format": "Standard",
      "totalSeats": 48
    },
    {
      "id": "s_m2_t2_20260314_1900",
      "movieId": "m2",
      "theaterId": "t2",
      "screenNumber": 3,
      "date": "2026-03-14",
      "time": "19:00",
      "format": "Standard",
      "totalSeats": 48
    },
    {
      "id": "s_m2_t2_20260314_2030",
      "movieId": "m2",
      "theaterId": "t2",
      "screenNumber": 3,
      "date": "2026-03-14",
      "time": "20:30",
      "format": "Standard",
      "totalSeats": 48
    },
    {
      "id": "s_m2_t2_20260315_1730",
      "movieId": "m2",
      "theaterId": "t2",
      "screenNumber": 3,
      "date": "2026-03-15",
      "time": "17:30",
      "format": "Standard",
      "totalSeats": 48
    },
    {
      "id": "s_m2_t2_20260315_1900",
      "movieId": "m2",
      "theaterId": "t2",
      "screenNumber": 3,
      "date": "2026-03-15",
      "time": "19:00",
      "format": "Standard",
      "totalSeats": 48
    },
    {
      "id": "s_m2_t2_20260315_2030",
      "movieId": "m2",
      "theaterId": "t2",
      "screenNumber": 3,
      "date": "2026-03-15",
      "time": "20:30",
      "format": "Standard",
      "totalSeats": 48
    },
    {
      "id": "s_m2_t2_20260316_1730",
      "movieId": "m2",
      "theaterId": "t2",
      "screenNumber": 3,
      "date": "2026-03-16",
      "time": "17:30",
      "format": "Standard",
      "totalSeats": 48
    },
    {
      "id": "s_m2_t2_20260316_1900",
      "movieId": "m2",
      "theaterId": "t2",
      "screenNumber": 3,
      "date": "2026-03-16",
      "time": "19:00",
      "format": "Standard",
      "totalSeats": 48
    },
    {
      "id": "s_m2_t2_20260316_2030",
      "movieId": "m2",
      "theaterId": "t2",
      "screenNumber": 3,
      "date": "2026-03-16",
      "time": "20:30",
      "format": "Standard",
      "totalSeats": 48
    },
    {
      "id": "s_m2_t1_20260312_1730",
      "movieId": "m2",
      "theaterId": "t1",
      "screenNumber": 2,
      "date": "2026-03-12",
      "time": "17:30",
      "format": "Standard",
      "totalSeats": 48
    },
    {
      "id": "s_m2_t1_20260312_1900",
      "movieId": "m2",
      "theaterId": "t1",
      "screenNumber": 2,
      "date": "2026-03-12",
      "time": "19:00",
      "format": "Standard",
      "totalSeats": 48
    },
    {
      "id": "s_m2_t1_20260312_2030",
      "movieId": "m2",
      "theaterId": "t1",
      "screenNumber": 2,
      "date": "2026-03-12",
      "time": "20:30",
      "format": "Standard",
      "totalSeats": 48
    },
    {
      "id": "s_m2_t1_20260313_1730",
      "movieId": "m2",
      "theaterId": "t1",
      "screenNumber": 2,
      "date": "2026-03-13",
      "time": "17:30",
      "format": "Standard",
      "totalSeats": 48
    },
    {
      "id": "s_m2_t1_20260313_1900",
      "movieId": "m2",
      "theaterId": "t1",
      "screenNumber": 2,
      "date": "2026-03-13",
      "time": "19:00",
      "format": "Standard",
      "totalSeats": 48
    },
    {
      "id": "s_m2_t1_20260313_2030",
      "movieId": "m2",
      "theaterId": "t1",
      "screenNumber": 2,
      "date": "2026-03-13",
      "time": "20:30",
      "format": "Standard",
      "totalSeats": 48
    },
    {
      "id": "s_m2_t1_20260314_1730",
      "movieId": "m2",
      "theaterId": "t1",
      "screenNumber": 2,
      "date": "2026-03-14",
      "time": "17:30",
      "format": "Standard",
      "totalSeats": 48
    },
    {
      "id": "s_m2_t1_20260314_1900",
      "movieId": "m2",
      "theaterId": "t1",
      "screenNumber": 2,
      "date": "2026-03-14",
      "time": "19:00",
      "format": "Standard",
      "totalSeats": 48
    },
    {
      "id": "s_m2_t1_20260314_2030",
      "movieId": "m2",
      "theaterId": "t1",
      "screenNumber": 2,
      "date": "2026-03-14",
      "time": "20:30",
      "format": "Standard",
      "totalSeats": 48
    },
    {
      "id": "s_m2_t1_20260315_1730",
      "movieId": "m2",
      "theaterId": "t1",
      "screenNumber": 2,
      "date": "2026-03-15",
      "time": "17:30",
      "format": "Standard",
      "totalSeats": 48
    },
    {
      "id": "s_m2_t1_20260315_1900",
      "movieId": "m2",
      "theaterId": "t1",
      "screenNumber": 2,
      "date": "2026-03-15",
      "time": "19:00",
      "format": "Standard",
      "totalSeats": 48
    },
    {
      "id": "s_m2_t1_20260315_2030",
      "movieId": "m2",
      "theaterId": "t1",
      "screenNumber": 2,
      "date": "2026-03-15",
      "time": "20:30",
      "format": "Standard",
      "totalSeats": 48
    },
    {
      "id": "s_m2_t1_20260316_1730",
      "movieId": "m2",
      "theaterId": "t1",
      "screenNumber": 2,
      "date": "2026-03-16",
      "time": "17:30",
      "format": "Standard",
      "totalSeats": 48
    },
    {
      "id": "s_m2_t1_20260316_1900",
      "movieId": "m2",
      "theaterId": "t1",
      "screenNumber": 2,
      "date": "2026-03-16",
      "time": "19:00",
      "format": "Standard",
      "totalSeats": 48
    },
    {
      "id": "s_m2_t1_20260316_2030",
      "movieId": "m2",
      "theaterId": "t1",
      "screenNumber": 2,
      "date": "2026-03-16",
      "time": "20:30",
      "format": "Standard",
      "totalSeats": 48
    }
  ],
  "seatTemplate": {
    "rows": [
      "A",
      "B",
      "C",
      "D",
      "E",
      "F"
    ],
    "seatsPerRow": 8,
    "defaultType": "standard",
    "defaultPrice": 15,
    "defaultStatus": "available"
  },
  "seatOverrides": [
    {
      "showingId": "s_m1_t2_20260313_1900",
      "row": "A",
      "occupiedNumbers": [
        1,
        3,
        4,
        6,
        7
      ]
    },
    {
      "showingId": "s_m1_t2_20260313_1900",
      "row": "B",
      "occupiedNumbers": [
        2,
        3,
        5,
        7,
        8
      ]
    },
    {
      "showingId": "s_m1_t2_20260313_1900",
      "row": "C",
      "occupiedNumbers": [
        1,
        3,
        5,
        6,
        8
      ]
    },
    {
      "showingId": "s_m1_t2_20260313_1900",
      "row": "D",
      "occupiedNumbers": [
        1,
        2,
        4,
        5,
        6,
        7
      ]
    },
    {
      "showingId": "s_m1_t2_20260313_1900",
      "row": "E",
      "occupiedNumbers": [
        1,
        2,
        3,
        6,
        7,
        8
      ]
    },
    {
      "showingId": "s_m1_t2_20260313_1900",
      "row": "F",
      "occupiedNumbers": [
        3,
        4,
        5,
        7,
        8
      ]
    },
    {
      "showingId": "s_m1_t1_20260313_1900",
      "row": "A",
      "occupiedNumbers": [
        2,
        3,
        5,
        7,
        8
      ]
    },
    {
      "showingId": "s_m1_t1_20260313_1900",
      "row": "B",
      "occupiedNumbers": [
        1,
        3,
        4,
        6,
        8
      ]
    },
    {
      "showingId": "s_m1_t1_20260313_1900",
      "row": "C",
      "occupiedNumbers": [
        2,
        4,
        5,
        6,
        7
      ]
    },
    {
      "showingId": "s_m1_t1_20260313_1900",
      "row": "D",
      "occupiedNumbers": [
        1,
        3,
        4,
        5,
        7,
        8
      ]
    },
    {
      "showingId": "s_m1_t1_20260313_1900",
      "row": "E",
      "occupiedNumbers": [
        1,
        2,
        5,
        6,
        8
      ]
    },
    {
      "showingId": "s_m1_t1_20260313_1900",
      "row": "F",
      "occupiedNumbers": [
        1,
        4,
        5,
        7,
        8
      ]
    },
    {
      "showingId": "s_m2_t2_20260313_1900",
      "row": "A",
      "occupiedNumbers": [
        2,
        3,
        4,
        6,
        7,
        8
      ]
    },
    {
      "showingId": "s_m2_t2_20260313_1900",
      "row": "B",
      "occupiedNumbers": [
        1,
        3,
        4,
        5,
        8
      ]
    },
    {
      "showingId": "s_m2_t2_20260313_1900",
      "row": "C",
      "occupiedNumbers": [
        1,
        2,
        5,
        6,
        8
      ]
    },
    {
      "showingId": "s_m2_t2_20260313_1900",
      "row": "D",
      "occupiedNumbers": [
        1,
        3,
        4,
        7,
        8
      ]
    },
    {
      "showingId": "s_m2_t2_20260313_1900",
      "row": "E",
      "occupiedNumbers": [
        2,
        3,
        4,
        5,
        6,
        7
      ]
    },
    {
      "showingId": "s_m2_t2_20260313_1900",
      "row": "F",
      "occupiedNumbers": [
        1,
        2,
        4,
        5,
        6,
        7,
        8
      ]
    },
    {
      "showingId": "s_m2_t1_20260313_1900",
      "row": "A",
      "occupiedNumbers": [
        1,
        3,
        4,
        5,
        7,
        8
      ]
    },
    {
      "showingId": "s_m2_t1_20260313_1900",
      "row": "B",
      "occupiedNumbers": [
        2,
        3,
        5,
        6,
        8
      ]
    },
    {
      "showingId": "s_m2_t1_20260313_1900",
      "row": "C",
      "occupiedNumbers": [
        1,
        4,
        5,
        7,
        8
      ]
    },
    {
      "showingId": "s_m2_t1_20260313_1900",
      "row": "D",
      "occupiedNumbers": [
        2,
        3,
        4,
        7,
        8
      ]
    },
    {
      "showingId": "s_m2_t1_20260313_1900",
      "row": "E",
      "occupiedNumbers": [
        1,
        3,
        4,
        5,
        6,
        8
      ]
    },
    {
      "showingId": "s_m2_t1_20260313_1900",
      "row": "F",
      "occupiedNumbers": [
        1,
        2,
        3,
        5,
        6,
        7,
        8
      ]
    },
    {
      "showingId": "s_m2_t2_20260313_2030",
      "row": "A",
      "occupiedNumbers": [
        1,
        3,
        4,
        5,
        7,
        8
      ]
    },
    {
      "showingId": "s_m2_t2_20260313_2030",
      "row": "B",
      "occupiedNumbers": [
        2,
        3,
        4,
        6,
        8
      ]
    },
    {
      "showingId": "s_m2_t2_20260313_2030",
      "row": "C",
      "occupiedNumbers": [
        1,
        3,
        4,
        5,
        6,
        8
      ]
    },
    {
      "showingId": "s_m2_t2_20260313_2030",
      "row": "D",
      "occupiedNumbers": [
        1,
        2,
        5,
        6,
        7
      ]
    },
    {
      "showingId": "s_m2_t2_20260313_2030",
      "row": "E",
      "occupiedNumbers": [
        2,
        3,
        4,
        5,
        7,
        8
      ]
    },
    {
      "showingId": "s_m2_t2_20260313_2030",
      "row": "F",
      "occupiedNumbers": [
        1,
        2,
        3,
        5,
        6,
        7,
        8
      ]
    },
    {
      "showingId": "s_m2_t1_20260313_2030",
      "row": "A",
      "occupiedNumbers": [
        2,
        3,
        4,
        6,
        7,
        8
      ]
    },
    {
      "showingId": "s_m2_t1_20260313_2030",
      "row": "B",
      "occupiedNumbers": [
        1,
        3,
        4,
        5,
        8
      ]
    },
    {
      "showingId": "s_m2_t1_20260313_2030",
      "row": "C",
      "occupiedNumbers": [
        1,
        2,
        4,
        5,
        7,
        8
      ]
    },
    {
      "showingId": "s_m2_t1_20260313_2030",
      "row": "D",
      "occupiedNumbers": [
        1,
        2,
        3,
        6,
        7
      ]
    },
    {
      "showingId": "s_m2_t1_20260313_2030",
      "row": "E",
      "occupiedNumbers": [
        1,
        3,
        4,
        5,
        6,
        8
      ]
    },
    {
      "showingId": "s_m2_t1_20260313_2030",
      "row": "F",
      "occupiedNumbers": [
        1,
        2,
        4,
        5,
        6,
        7,
        8
      ]
    }
  ],
  "assertions": {
    "expectedMovieIds": [
      "m3",
      "m4",
      "m1",
      "m2"
    ],
    "expectedTheaterIds": [
      "t2",
      "t1"
    ],
    "theaterDistanceChecks": [
      {
        "theaterId": "t2",
        "distanceMiles": 8.2
      },
      {
        "theaterId": "t1",
        "distanceMiles": 3.4
      }
    ],
    "dateRules": [
      {
        "movieId": "m3",
        "theaterId": "t2",
        "expectedDates": [
          "2026-03-12",
          "2026-03-13",
          "2026-03-14",
          "2026-03-15",
          "2026-03-16"
        ]
      },
      {
        "movieId": "m3",
        "theaterId": "t1",
        "expectedDates": [
          "2026-03-12",
          "2026-03-13",
          "2026-03-14",
          "2026-03-15",
          "2026-03-16"
        ]
      },
      {
        "movieId": "m4",
        "theaterId": "t2",
        "expectedDates": [
          "2026-03-12",
          "2026-03-13",
          "2026-03-14",
          "2026-03-15",
          "2026-03-16"
        ]
      },
      {
        "movieId": "m4",
        "theaterId": "t1",
        "expectedDates": [
          "2026-03-12",
          "2026-03-13",
          "2026-03-14",
          "2026-03-15",
          "2026-03-16"
        ]
      },
      {
        "movieId": "m1",
        "theaterId": "t2",
        "expectedDates": [
          "2026-03-12",
          "2026-03-13",
          "2026-03-14",
          "2026-03-15",
          "2026-03-16"
        ]
      },
      {
        "movieId": "m1",
        "theaterId": "t1",
        "expectedDates": [
          "2026-03-12",
          "2026-03-13",
          "2026-03-14",
          "2026-03-15",
          "2026-03-16"
        ]
      },
      {
        "movieId": "m2",
        "theaterId": "t2",
        "expectedDates": [
          "2026-03-12",
          "2026-03-13",
          "2026-03-14",
          "2026-03-15",
          "2026-03-16"
        ]
      },
      {
        "movieId": "m2",
        "theaterId": "t1",
        "expectedDates": [
          "2026-03-12",
          "2026-03-13",
          "2026-03-14",
          "2026-03-15",
          "2026-03-16"
        ]
      }
    ],
    "timeRules": [
      {
        "movieId": "m1",
        "theaterId": "t2",
        "date": "2026-03-13",
        "expectedShowings": [
          {
            "time": "17:30",
            "format": "Standard"
          },
          {
            "time": "19:00",
            "format": "Standard"
          },
          {
            "time": "20:30",
            "format": "Standard"
          }
        ]
      },
      {
        "movieId": "m2",
        "theaterId": "t2",
        "date": "2026-03-13",
        "expectedShowings": [
          {
            "time": "17:30",
            "format": "Standard"
          },
          {
            "time": "19:00",
            "format": "Standard"
          },
          {
            "time": "20:30",
            "format": "Standard"
          }
        ]
      },
      {
        "movieId": "m1",
        "theaterId": "t1",
        "date": "2026-03-13",
        "expectedShowings": [
          {
            "time": "17:30",
            "format": "Standard"
          },
          {
            "time": "19:00",
            "format": "Standard"
          },
          {
            "time": "20:30",
            "format": "Standard"
          }
        ]
      },
      {
        "movieId": "m2",
        "theaterId": "t1",
        "date": "2026-03-13",
        "expectedShowings": [
          {
            "time": "17:30",
            "format": "Standard"
          },
          {
            "time": "19:00",
            "format": "Standard"
          },
          {
            "time": "20:30",
            "format": "Standard"
          }
        ]
      }
    ],
    "adjacencyRules": [
      {
        "showingId": "s_m1_t2_20260313_1900",
        "row": "D",
        "maxAdjacentAvailable": 1
      },
      {
        "showingId": "s_m1_t2_20260313_1900",
        "row": "E",
        "minAdjacentAvailable": 2
      },
      {
        "showingId": "s_m2_t2_20260313_1900",
        "row": "C",
        "minAdjacentAvailable": 2
      },
      {
        "showingId": "s_m2_t2_20260313_2030",
        "row": "D",
        "minAdjacentAvailable": 2
      },
      {
        "showingId": "s_m1_t1_20260313_1900",
        "row": "D",
        "maxAdjacentAvailable": 1
      },
      {
        "showingId": "s_m1_t1_20260313_1900",
        "row": "E",
        "minAdjacentAvailable": 2
      },
      {
        "showingId": "s_m2_t1_20260313_1900",
        "row": "C",
        "minAdjacentAvailable": 2
      },
      {
        "showingId": "s_m2_t1_20260313_2030",
        "row": "D",
        "minAdjacentAvailable": 2
      }
    ],
    "seatAvailabilityRules": [
      {
        "showingId": "s_m1_t2_20260313_1900",
        "row": "A",
        "expectedAvailableNumbers": [
          2,
          5,
          8
        ]
      },
      {
        "showingId": "s_m1_t2_20260313_1900",
        "row": "B",
        "expectedAvailableNumbers": [
          1,
          4,
          6
        ]
      },
      {
        "showingId": "s_m1_t2_20260313_1900",
        "row": "C",
        "expectedAvailableNumbers": [
          2,
          4,
          7
        ]
      },
      {
        "showingId": "s_m1_t2_20260313_1900",
        "row": "D",
        "expectedAvailableNumbers": [
          3,
          8
        ]
      },
      {
        "showingId": "s_m1_t2_20260313_1900",
        "row": "E",
        "expectedAvailableNumbers": [
          4,
          5
        ]
      },
      {
        "showingId": "s_m2_t2_20260313_1900",
        "row": "C",
        "expectedAvailableNumbers": [
          3,
          4,
          7
        ]
      },
      {
        "showingId": "s_m2_t2_20260313_1900",
        "row": "D",
        "expectedAvailableNumbers": [
          2,
          5,
          6
        ]
      },
      {
        "showingId": "s_m2_t2_20260313_2030",
        "row": "D",
        "expectedAvailableNumbers": [
          3,
          4,
          8
        ]
      },
      {
        "showingId": "s_m1_t1_20260313_1900",
        "row": "A",
        "expectedAvailableNumbers": [
          1,
          4,
          6
        ]
      },
      {
        "showingId": "s_m1_t1_20260313_1900",
        "row": "B",
        "expectedAvailableNumbers": [
          2,
          5,
          7
        ]
      },
      {
        "showingId": "s_m1_t1_20260313_1900",
        "row": "C",
        "expectedAvailableNumbers": [
          1,
          3,
          8
        ]
      },
      {
        "showingId": "s_m1_t1_20260313_1900",
        "row": "D",
        "expectedAvailableNumbers": [
          2,
          6
        ]
      },
      {
        "showingId": "s_m1_t1_20260313_1900",
        "row": "E",
        "expectedAvailableNumbers": [
          3,
          4,
          7
        ]
      },
      {
        "showingId": "s_m2_t1_20260313_1900",
        "row": "C",
        "expectedAvailableNumbers": [
          2,
          3,
          6
        ]
      },
      {
        "showingId": "s_m2_t1_20260313_1900",
        "row": "D",
        "expectedAvailableNumbers": [
          1,
          5,
          6
        ]
      },
      {
        "showingId": "s_m2_t1_20260313_2030",
        "row": "D",
        "expectedAvailableNumbers": [
          4,
          5,
          8
        ]
      }
    ]
  }
}
